oct_vesselseg/__init__.py
oct_vesselseg/attenuators.py
oct_vesselseg/callbacks.py
oct_vesselseg/client.py
oct_vesselseg/data.py
oct_vesselseg/frangi.py
oct_vesselseg/losses.py
oct_vesselseg/main.py
oct_vesselseg/models.py
oct_vesselseg/modules.py
oct_vesselseg/serve_predict.py
oct_vesselseg/server.py
oct_vesselseg/synth.py
oct_vesselseg/train.py
oct_vesselseg/utils.py
oct_vesselseg-0.1.0.dist-info/licenses/LICENSE
tests/__init__.py
tests/test_imagesynth.py
tests/test_main.py
tests/test_vesselsynth.py
oct_vesselseg-0.1.0.dist-info/METADATA
oct_vesselseg-0.1.0.dist-info/WHEEL
oct_vesselseg-0.1.0.dist-info/entry_points.txt
oct_vesselseg-0.1.0.dist-info/top_level.txt
oct_vesselseg-0.1.0.dist-info/RECORD
