Metadata-Version: 2.4
Name: oct_vesselseg
Version: 0.1.0
Summary: A Label-Free and Data-Free Synthesis Engine and Training Framework for Vascular Segmentation of sOCT Data with PyTorch.
Author: Etienne Chollet & Yaël Balbastre
Author-email: etiennepchollet@gmail.com
Project-URL: Conference Preprint, https://arxiv.org/abs/2405.13757v1
Project-URL: Paper Preprint, https://arxiv.org/abs/2407.01419v1
Project-URL: Source, https://github.com/EtienneChollet/oct_vesselseg
Classifier: Development Status :: 4 - Beta
Classifier: Intended Audience :: Science/Research
Classifier: Topic :: Software Development :: Build Tools
Classifier: License :: OSI Approved :: MIT License
Classifier: Programming Language :: Python :: 3.9
Requires-Python: ~=3.9
License-File: LICENSE
Requires-Dist: cyclopts
Provides-Extra: client
Requires-Dist: fastapi; extra == "client"
Requires-Dist: python-multipart; extra == "client"
Requires-Dist: uvicorn; extra == "client"
Requires-Dist: requests; extra == "client"
Provides-Extra: server
Requires-Dist: cupy-cuda11x; extra == "server"
Requires-Dist: cppyy==2.3; extra == "server"
Requires-Dist: torch; extra == "server"
Requires-Dist: torchvision; extra == "server"
Requires-Dist: torchaudio; extra == "server"
Requires-Dist: torchmetrics; extra == "server"
Requires-Dist: jitfields; extra == "server"
Requires-Dist: torch-interpol; extra == "server"
Requires-Dist: torch-distmap; extra == "server"
Requires-Dist: nibabel; extra == "server"
Requires-Dist: pytorch-lightning; extra == "server"
Requires-Dist: scikit-learn; extra == "server"
Requires-Dist: matplotlib; extra == "server"
Requires-Dist: tensorboard; extra == "server"
Requires-Dist: pandas; extra == "server"
Requires-Dist: cyclopts; extra == "server"
Requires-Dist: cornucopia; extra == "server"
Dynamic: author
Dynamic: author-email
Dynamic: classifier
Dynamic: description
Dynamic: description-content-type
Dynamic: license-file
Dynamic: project-url
Dynamic: provides-extra
Dynamic: requires-dist
Dynamic: requires-python
Dynamic: summary
